mystique/__init__.py
mystique/matcher.py
mystique/predicates.py
mystique-0.4.0.dist-info/METADATA
mystique-0.4.0.dist-info/WHEEL
mystique-0.4.0.dist-info/licenses/LICENSE
mystique-0.4.0.dist-info/RECORD
