Metadata-Version: 2.3
Name: mystique
Version: 0.4.0
Summary: A loose data matcher to help you write Python tests
Project-URL: Homepage, https://github.com/jonocodes/mystique
Project-URL: Bug Tracker, https://github.com/jonocodes/mystique/issues
Author-email: Jono Finger <jono@foodnotblogs.com>
License-File: LICENSE
Classifier: License :: OSI Approved :: MIT License
Classifier: Operating System :: OS Independent
Classifier: Programming Language :: Python :: 3
Requires-Python: >=3.7
Requires-Dist: beartype==0.18.5
Requires-Dist: deepdiff==7.0.1
